frida_definitions_generator/__init__.py
frida_definitions_generator/__main__.py
frida_definitions_generator/_identifier.py
frida_definitions_generator-0.3.0.dist-info/LICENSE
frida_definitions_generator-0.3.0.dist-info/METADATA
frida_definitions_generator-0.3.0.dist-info/WHEEL
frida_definitions_generator-0.3.0.dist-info/entry_points.txt
frida_definitions_generator-0.3.0.dist-info/top_level.txt
frida_definitions_generator-0.3.0.dist-info/zip-safe
frida_definitions_generator-0.3.0.dist-info/RECORD
