Metadata-Version: 2.1
Name: frida-definitions-generator
Version: 0.3.0
Summary: Generate TypeScript definition files for use with Frida
Home-page: https://git.sr.ht/~yotam/frida-definitions-generator
Author: Yotam Nachum
Author-email: me@yotam.net
License: MIT
Keywords: frida,java,android,generation
Classifier: Development Status :: 3 - Alpha
Classifier: Environment :: Console
Classifier: License :: OSI Approved :: MIT License
Classifier: Programming Language :: Python :: 3
Classifier: Programming Language :: Python :: 3.8
Classifier: Programming Language :: Python :: 3.9
Classifier: Programming Language :: Python :: 3.10
Classifier: Programming Language :: Python :: 3.11
Classifier: Topic :: Software Development :: Code Generators
Classifier: Intended Audience :: Science/Research
Classifier: Intended Audience :: Developers
Requires-Python: >=3.8
License-File: LICENSE
Requires-Dist: lief (>=0.12.0)
